Metadata-Version: 2.1
Name: serial-fingers-control
Version: 0.0.1
Summary: Finger control for STM32 old Api
Home-page: https://github.com/Adam-Software/Serial-fingers-control
Author: vertigra
Author-email: a@nesterof.com
License: MIT
Platform: UNKNOWN
Classifier: Development Status :: 3 - Alpha
Classifier: License :: OSI Approved :: MIT License
Classifier: Operating System :: POSIX :: Linux
Classifier: Programming Language :: Python :: 3.8
Classifier: Programming Language :: Python :: 3.9
License-File: LICENSE
